mcp_server_weather/ __main__.py
mcp_server_weather/__init__.py
mcp_server_weather/server.py
hadron_mcp_server_weather-0.1.1.dist-info/METADATA
hadron_mcp_server_weather-0.1.1.dist-info/WHEEL
hadron_mcp_server_weather-0.1.1.dist-info/entry_points.txt
hadron_mcp_server_weather-0.1.1.dist-info/top_level.txt
hadron_mcp_server_weather-0.1.1.dist-info/RECORD
