Metadata-Version: 2.4
Name: hadron-mcp-server-weather
Version: 0.1.1
Summary: 实现类weather功能的MCP⼯具
Requires-Python: >=3.10
Requires-Dist: dotenv>=0.9.9
Requires-Dist: mcp>=1.13.1
Requires-Dist: openai>=1.107.0
